Allinoneincluding/Allinone.py
Allinoneincluding/__init__.py
Allinoneincluding/book.py
Allinoneincluding/calculator.py
Allinoneincluding/erfenchazhao_py.py
Allinoneincluding/math_cal_py.py
Allinoneincluding/student_py.py
Allinoneincluding/tuxing_cal.py
Allinoneincluding/xiaogongju.py
Allinoneincluding-4.1.5.dist-info/LICENSE
Allinoneincluding-4.1.5.dist-info/METADATA
Allinoneincluding-4.1.5.dist-info/WHEEL
Allinoneincluding-4.1.5.dist-info/top_level.txt
Allinoneincluding-4.1.5.dist-info/RECORD
