Metadata-Version: 2.1
Name: Allinoneincluding
Version: 4.1.5
Summary: 多功能一体机（All-in-one）
Home-page: https://github.com/lichenyichay/All-in-one-Including/
Author: Chay
Author-email: chay <lichenyi_2020@qq.com>
Project-URL: Homepage, https://github.com/lichenyichay/All-in-one-Including/
Project-URL: Issues, https://github.com/lichenyichay/All-in-one-Including/issues
Classifier: Programming Language :: Python :: 3
Classifier: License :: OSI Approved :: MIT License
Classifier: Operating System :: OS Independent
Requires-Python: >=3.5
License-File: LICENSE
